README.md
setup.py
py_util/__init__.py
py_util/excel.py
py_util.egg-info/PKG-INFO
py_util.egg-info/SOURCES.txt
py_util.egg-info/dependency_links.txt
py_util.egg-info/requires.txt
py_util.egg-info/top_level.txt
tests/__init__.py
tests/test_excel.py