Metadata-Version: 2.1
Name: py-util
Version: 0.1.1
Summary: Python tools
Home-page: https://github.com/hotbaby/py-util
Author: Meng yangyang
Author-email: mengyy_linux@163.com
License: MIT
Platform: UNKNOWN
Classifier: Programming Language :: Python :: 2
Classifier: License :: OSI Approved :: MIT License
Classifier: Operating System :: OS Independent
